google-cloud-publisher/__init__.py
google-cloud-publisher/publisher.py
google-cloud-publisher/test_publisher.py
google_cloud_publisher/__init__.py
google_cloud_publisher/publisher.py
google_cloud_publisher/test_publisher.py
google_cloud_publisher-0.0.2.dist-info/METADATA
google_cloud_publisher-0.0.2.dist-info/RECORD
google_cloud_publisher-0.0.2.dist-info/WHEEL
google_cloud_publisher-0.0.2.dist-info/top_level.txt
